{
  "collectionName": "components_banner_banners",
  "info": {
    "displayName": "banner"
  },
  "options": {},
  "attributes": {
    "title": {
      "type": "string"
    },
    "description": {
      "type": "text"
    },
    "button": {
      "type": "component",
      "repeatable": true,
      "component": "button.button"
    },
    "image": {
      "allowedTypes": [
        "images",
        "files",
        "videos",
        "audios"
      ],
      "type": "media",
      "multiple": true
    },
    "Backgroundimage": {
      "allowedTypes": [
        "images",
        "files",
        "videos",
        "audios"
      ],
      "type": "media",
      "multiple": true
    },
    "color": {
      "type": "json"
    }
  }
}
